README.md
setup.py
py_html_graph/__init__.py
py_html_graph/colors.py
py_html_graph/forwarder.py
py_html_graph/htmls.py
py_html_graph/server.py
py_html_graph.egg-info/PKG-INFO
py_html_graph.egg-info/SOURCES.txt
py_html_graph.egg-info/dependency_links.txt
py_html_graph.egg-info/requires.txt
py_html_graph.egg-info/top_level.txt
py_html_graph/html/404.html
py_html_graph/html/axis.js
py_html_graph/html/cache_worker.js
py_html_graph/html/chart.js
py_html_graph/html/dash.html
py_html_graph/html/forward.html
py_html_graph/html/http.js
py_html_graph/html/main.css
py_html_graph/html/main.html
py_html_graph/html/main.js
py_html_graph/html/reset.css
py_html_graph/html/style.js
py_html_graph/ssl/certificate.crt
py_html_graph/ssl/private.key