Metadata-Version: 2.1
Name: py-html-graph
Version: 0.1.0
Summary: A high-performance interactive numpy line chart viewer, good supplement for the awful matplotlib.
Home-page: https://github.com/jtc1246/py-html-graph
Author: Tiancheng Jiao
Author-email: jtc1246@outlook.com
License: GPL-2.0 License
Platform: all
Requires-Python: >=3.9
